aes/shift_rows.v
module ShiftRows(
	input i_clock,
	input [0:127] i_data,
	input i_active,
	output [0:127] o_data
);

reg [0:127] r_data;

always @(posedge i_clock) begin
	if (i_active) begin
		r_data[0:7] <= i_data[0:7];
		r_data[8:15] <= i_data[8:15];
		r_data[16:23] <= i_data[16:23];
		r_data[24:31] <= i_data[24:31];

		r_data[32:39] <= i_data[40:47];
		r_data[40:47] <= i_data[48:55];
		r_data[48:55] <= i_data[56:63];
		r_data[56:63] <= i_data[32:39];

		r_data[64:71] <= i_data[80:87];
		r_data[72:79] <= i_data[88:95];
		r_data[80:87] <= i_data[64:71];
		r_data[88:95] <= i_data[72:79];

		r_data[96:103] <= i_data[120:127];
		r_data[104:111] <= i_data[96:103];
		r_data[112:119] <= i_data[104:111];
		r_data[120:127] <= i_data[112:119];
	end
end

assign o_data = r_data;

endmodule

aes/sub_bytes.v
module SubBytes(
	input i_clock,
	input [0:127] i_data,
	input i_active,
	output [0:127] o_data
);

reg [0:127] r_data;
// reg [0:7] r_state [0:15];
wire [0:7] sbox [0:255];

always @(posedge i_clock) begin
	if (i_active) begin
		r_data[0:7] <= sbox[i_data[0:7]];
		r_data[8:15] <= sbox[i_data[8:15]];
		r_data[16:23] <= sbox[i_data[16:23]];
		r_data[24:31] <= sbox[i_data[24:31]];
		r_data[32:39] <= sbox[i_data[32:39]];
		r_data[40:47] <= sbox[i_data[40:47]];
		r_data[48:55] <= sbox[i_data[48:55]];
		r_data[56:63] <= sbox[i_data[56:63]];
		r_data[64:71] <= sbox[i_data[64:71]];
		r_data[72:79] <= sbox[i_data[72:79]];
		r_data[80:87] <= sbox[i_data[80:87]];
		r_data[88:95] <= sbox[i_data[88:95]];
		r_data[96:103] <= sbox[i_data[96:103]];
		r_data[104:111] <= sbox[i_data[104:111]];
		r_data[112:119] <= sbox[i_data[112:119]];
		r_data[120:127] <= sbox[i_data[120:127]];
	end
end

assign o_data = r_data;

assign sbox[8'h00] = 8'h63;
assign sbox[8'h01] = 8'h7c;
assign sbox[8'h02] = 8'h77;
assign sbox[8'h03] = 8'h7b;
assign sbox[8'h04] = 8'hf2;
assign sbox[8'h05] = 8'h6b;
assign sbox[8'h06] = 8'h6f;
assign sbox[8'h07] = 8'hc5;
assign sbox[8'h08] = 8'h30;
assign sbox[8'h09] = 8'h01;
assign sbox[8'h0a] = 8'h67;
assign sbox[8'h0b] = 8'h2b;
assign sbox[8'h0c] = 8'hfe;
assign sbox[8'h0d] = 8'hd7;
assign sbox[8'h0e] = 8'hab;
assign sbox[8'h0f] = 8'h76;
assign sbox[8'h10] = 8'hca;
assign sbox[8'h11] = 8'h82;
assign sbox[8'h12] = 8'hc9;
assign sbox[8'h13] = 8'h7d;
assign sbox[8'h14] = 8'hfa;
assign sbox[8'h15] = 8'h59;
assign sbox[8'h16] = 8'h47;
assign sbox[8'h17] = 8'hf0;
assign sbox[8'h18] = 8'had;
assign sbox[8'h19] = 8'hd4;
assign sbox[8'h1a] = 8'ha2;
assign sbox[8'h1b] = 8'haf;
assign sbox[8'h1c] = 8'h9c;
assign sbox[8'h1d] = 8'ha4;
assign sbox[8'h1e] = 8'h72;
assign sbox[8'h1f] = 8'hc0;
assign sbox[8'h20] = 8'hb7;
assign sbox[8'h21] = 8'hfd;
assign sbox[8'h22] = 8'h93;
assign sbox[8'h23] = 8'h26;
assign sbox[8'h24] = 8'h36;
assign sbox[8'h25] = 8'h3f;
assign sbox[8'h26] = 8'hf7;
assign sbox[8'h27] = 8'hcc;
assign sbox[8'h28] = 8'h34;
assign sbox[8'h29] = 8'ha5;
assign sbox[8'h2a] = 8'he5;
assign sbox[8'h2b] = 8'hf1;
assign sbox[8'h2c] = 8'h71;
assign sbox[8'h2d] = 8'hd8;
assign sbox[8'h2e] = 8'h31;
assign sbox[8'h2f] = 8'h15;
assign sbox[8'h30] = 8'h04;
assign sbox[8'h31] = 8'hc7;
assign sbox[8'h32] = 8'h23;
assign sbox[8'h33] = 8'hc3;
assign sbox[8'h34] = 8'h18;
assign sbox[8'h35] = 8'h96;
assign sbox[8'h36] = 8'h05;
assign sbox[8'h37] = 8'h9a;
assign sbox[8'h38] = 8'h07;
assign sbox[8'h39] = 8'h12;
assign sbox[8'h3a] = 8'h80;
assign sbox[8'h3b] = 8'he2;
assign sbox[8'h3c] = 8'heb;
assign sbox[8'h3d] = 8'h27;
assign sbox[8'h3e] = 8'hb2;
assign sbox[8'h3f] = 8'h75;
assign sbox[8'h40] = 8'h09;
assign sbox[8'h41] = 8'h83;
assign sbox[8'h42] = 8'h2c;
assign sbox[8'h43] = 8'h1a;
assign sbox[8'h44] = 8'h1b;
assign sbox[8'h45] = 8'h6e;
assign sbox[8'h46] = 8'h5a;
assign sbox[8'h47] = 8'ha0;
assign sbox[8'h48] = 8'h52;
assign sbox[8'h49] = 8'h3b;
assign sbox[8'h4a] = 8'hd6;
assign sbox[8'h4b] = 8'hb3;
assign sbox[8'h4c] = 8'h29;
assign sbox[8'h4d] = 8'he3;
assign sbox[8'h4e] = 8'h2f;
assign sbox[8'h4f] = 8'h84;
assign sbox[8'h50] = 8'h53;
assign sbox[8'h51] = 8'hd1;
assign sbox[8'h52] = 8'h00;
assign sbox[8'h53] = 8'hed;
assign sbox[8'h54] = 8'h20;
assign sbox[8'h55] = 8'hfc;
assign sbox[8'h56] = 8'hb1;
assign sbox[8'h57] = 8'h5b;
assign sbox[8'h58] = 8'h6a;
assign sbox[8'h59] = 8'hcb;
assign sbox[8'h5a] = 8'hbe;
assign sbox[8'h5b] = 8'h39;
assign sbox[8'h5c] = 8'h4a;
assign sbox[8'h5d] = 8'h4c;
assign sbox[8'h5e] = 8'h58;
assign sbox[8'h5f] = 8'hcf;
assign sbox[8'h60] = 8'hd0;
assign sbox[8'h61] = 8'hef;
assign sbox[8'h62] = 8'haa;
assign sbox[8'h63] = 8'hfb;
assign sbox[8'h64] = 8'h43;
assign sbox[8'h65] = 8'h4d;
assign sbox[8'h66] = 8'h33;
assign sbox[8'h67] = 8'h85;
assign sbox[8'h68] = 8'h45;
assign sbox[8'h69] = 8'hf9;
assign sbox[8'h6a] = 8'h02;
assign sbox[8'h6b] = 8'h7f;
assign sbox[8'h6c] = 8'h50;
assign sbox[8'h6d] = 8'h3c;
assign sbox[8'h6e] = 8'h9f;
assign sbox[8'h6f] = 8'ha8;
assign sbox[8'h70] = 8'h51;
assign sbox[8'h71] = 8'ha3;
assign sbox[8'h72] = 8'h40;
assign sbox[8'h73] = 8'h8f;
assign sbox[8'h74] = 8'h92;
assign sbox[8'h75] = 8'h9d;
assign sbox[8'h76] = 8'h38;
assign sbox[8'h77] = 8'hf5;
assign sbox[8'h78] = 8'hbc;
assign sbox[8'h79] = 8'hb6;
assign sbox[8'h7a] = 8'hda;
assign sbox[8'h7b] = 8'h21;
assign sbox[8'h7c] = 8'h10;
assign sbox[8'h7d] = 8'hff;
assign sbox[8'h7e] = 8'hf3;
assign sbox[8'h7f] = 8'hd2;
assign sbox[8'h80] = 8'hcd;
assign sbox[8'h81] = 8'h0c;
assign sbox[8'h82] = 8'h13;
assign sbox[8'h83] = 8'hec;
assign sbox[8'h84] = 8'h5f;
assign sbox[8'h85] = 8'h97;
assign sbox[8'h86] = 8'h44;
assign sbox[8'h87] = 8'h17;
assign sbox[8'h88] = 8'hc4;
assign sbox[8'h89] = 8'ha7;
assign sbox[8'h8a] = 8'h7e;
assign sbox[8'h8b] = 8'h3d;
assign sbox[8'h8c] = 8'h64;
assign sbox[8'h8d] = 8'h5d;
assign sbox[8'h8e] = 8'h19;
assign sbox[8'h8f] = 8'h73;
assign sbox[8'h90] = 8'h60;
assign sbox[8'h91] = 8'h81;
assign sbox[8'h92] = 8'h4f;
assign sbox[8'h93] = 8'hdc;
assign sbox[8'h94] = 8'h22;
assign sbox[8'h95] = 8'h2a;
assign sbox[8'h96] = 8'h90;
assign sbox[8'h97] = 8'h88;
assign sbox[8'h98] = 8'h46;
assign sbox[8'h99] = 8'hee;
assign sbox[8'h9a] = 8'hb8;
assign sbox[8'h9b] = 8'h14;
assign sbox[8'h9c] = 8'hde;
assign sbox[8'h9d] = 8'h5e;
assign sbox[8'h9e] = 8'h0b;
assign sbox[8'h9f] = 8'hdb;
assign sbox[8'ha0] = 8'he0;
assign sbox[8'ha1] = 8'h32;
assign sbox[8'ha2] = 8'h3a;
assign sbox[8'ha3] = 8'h0a;
assign sbox[8'ha4] = 8'h49;
assign sbox[8'ha5] = 8'h06;
assign sbox[8'ha6] = 8'h24;
assign sbox[8'ha7] = 8'h5c;
assign sbox[8'ha8] = 8'hc2;
assign sbox[8'ha9] = 8'hd3;
assign sbox[8'haa] = 8'hac;
assign sbox[8'hab] = 8'h62;
assign sbox[8'hac] = 8'h91;
assign sbox[8'had] = 8'h95;
assign sbox[8'hae] = 8'he4;
assign sbox[8'haf] = 8'h79;
assign sbox[8'hb0] = 8'he7;
assign sbox[8'hb1] = 8'hc8;
assign sbox[8'hb2] = 8'h37;
assign sbox[8'hb3] = 8'h6d;
assign sbox[8'hb4] = 8'h8d;
assign sbox[8'hb5] = 8'hd5;
assign sbox[8'hb6] = 8'h4e;
assign sbox[8'hb7] = 8'ha9;
assign sbox[8'hb8] = 8'h6c;
assign sbox[8'hb9] = 8'h56;
assign sbox[8'hba] = 8'hf4;
assign sbox[8'hbb] = 8'hea;
assign sbox[8'hbc] = 8'h65;
assign sbox[8'hbd] = 8'h7a;
assign sbox[8'hbe] = 8'hae;
assign sbox[8'hbf] = 8'h08;
assign sbox[8'hc0] = 8'hba;
assign sbox[8'hc1] = 8'h78;
assign sbox[8'hc2] = 8'h25;
assign sbox[8'hc3] = 8'h2e;
assign sbox[8'hc4] = 8'h1c;
assign sbox[8'hc5] = 8'ha6;
assign sbox[8'hc6] = 8'hb4;
assign sbox[8'hc7] = 8'hc6;
assign sbox[8'hc8] = 8'he8;
assign sbox[8'hc9] = 8'hdd;
assign sbox[8'hca] = 8'h74;
assign sbox[8'hcb] = 8'h1f;
assign sbox[8'hcc] = 8'h4b;
assign sbox[8'hcd] = 8'hbd;
assign sbox[8'hce] = 8'h8b;
assign sbox[8'hcf] = 8'h8a;
assign sbox[8'hd0] = 8'h70;
assign sbox[8'hd1] = 8'h3e;
assign sbox[8'hd2] = 8'hb5;
assign sbox[8'hd3] = 8'h66;
assign sbox[8'hd4] = 8'h48;
assign sbox[8'hd5] = 8'h03;
assign sbox[8'hd6] = 8'hf6;
assign sbox[8'hd7] = 8'h0e;
assign sbox[8'hd8] = 8'h61;
assign sbox[8'hd9] = 8'h35;
assign sbox[8'hda] = 8'h57;
assign sbox[8'hdb] = 8'hb9;
assign sbox[8'hdc] = 8'h86;
assign sbox[8'hdd] = 8'hc1;
assign sbox[8'hde] = 8'h1d;
assign sbox[8'hdf] = 8'h9e;
assign sbox[8'he0] = 8'he1;
assign sbox[8'he1] = 8'hf8;
assign sbox[8'he2] = 8'h98;
assign sbox[8'he3] = 8'h11;
assign sbox[8'he4] = 8'h69;
assign sbox[8'he5] = 8'hd9;
assign sbox[8'he6] = 8'h8e;
assign sbox[8'he7] = 8'h94;
assign sbox[8'he8] = 8'h9b;
assign sbox[8'he9] = 8'h1e;
assign sbox[8'hea] = 8'h87;
assign sbox[8'heb] = 8'he9;
assign sbox[8'hec] = 8'hce;
assign sbox[8'hed] = 8'h55;
assign sbox[8'hee] = 8'h28;
assign sbox[8'hef] = 8'hdf;
assign sbox[8'hf0] = 8'h8c;
assign sbox[8'hf1] = 8'ha1;
assign sbox[8'hf2] = 8'h89;
assign sbox[8'hf3] = 8'h0d;
assign sbox[8'hf4] = 8'hbf;
assign sbox[8'hf5] = 8'he6;
assign sbox[8'hf6] = 8'h42;
assign sbox[8'hf7] = 8'h68;
assign sbox[8'hf8] = 8'h41;
assign sbox[8'hf9] = 8'h99;
assign sbox[8'hfa] = 8'h2d;
assign sbox[8'hfb] = 8'h0f;
assign sbox[8'hfc] = 8'hb0;
assign sbox[8'hfd] = 8'h54;
assign sbox[8'hfe] = 8'hbb;
assign sbox[8'hff] = 8'h16;

endmodule

aes/aes.v

`include "sub_bytes.v"
`include "shift_rows.v"

module aes_top(
	input i_clock,
	input [0:127] i_plain,
	input [0:127] i_key,
	output [0:127] o_cipher
);

parameter s_INIT			= 3'b000;
parameter s_LOAD_INPUT		= 3'b001;
parameter s_SUB_BYTES 		= 3'b010;
parameter s_SHIFT_ROWS 		= 3'b011;
parameter s_MIX_COLUMNS		= 3'b100;
parameter s_ADD_ROUND_KEY	= 3'b101;

reg [2:0] r_sm_main = 0;

reg [0:7] state [0:15];
reg [0:127] r_data = 0;
wire [0:127] w_data_o_sub_byte;
wire [0:127] w_data_o_shift_rows;
reg r_sub_bytes_active = 0;
reg r_shift_rows_active = 0;
reg [0:2] clock_counter = 0;

SubBytes sub_bytes (
	.i_clock(i_clock),
	.i_data(r_data),
	.i_active(r_sub_bytes_active),
	.o_data(w_data_o_sub_byte)
);

ShiftRows shift_rows (
	.i_clock(i_clock),
	.i_data(r_data),
	.i_active(r_shift_rows_active),
	.o_data(w_data_o_shift_rows)
);

always @(posedge i_clock) begin
	case (r_sm_main)
		s_INIT :
			begin
				r_sm_main <= s_LOAD_INPUT;
			end
		s_LOAD_INPUT : // 001
			begin
				r_data <= i_plain;
				r_sm_main <= s_SUB_BYTES;
			end
		s_SUB_BYTES : // 010
			begin
				clock_counter = clock_counter + 1;
				r_sub_bytes_active <= 1'b1;
				if (clock_counter == 3) begin
					r_data <= w_data_o_sub_byte;
					r_sub_bytes_active <= 1'b0;
					clock_counter <= 0;
					r_sm_main <= s_SHIFT_ROWS;
				end
			end
		s_SHIFT_ROWS : // 011
			begin
				clock_counter = clock_counter + 1;
				r_shift_rows_active <= 1'b1;
				if (clock_counter == 3) begin
					r_data <= w_data_o_shift_rows;
					r_shift_rows_active <= 1'b0;
					clock_counter <= 0;
					r_sm_main <= s_MIX_COLUMNS;
				end
			end
		s_MIX_COLUMNS :
			begin
				
			end
	endcase
end

always @(r_data) begin
	state[0] <= r_data[0:7];
	state[1] <= r_data[8:15];
	state[2] <= r_data[16:23];
	state[3] <= r_data[24:31];
	state[4] <= r_data[32:39];
	state[5] <= r_data[40:47];
	state[6] <= r_data[48:55];
	state[7] <= r_data[56:63];
	state[8] <= r_data[64:71];
	state[9] <= r_data[72:79];
	state[10] <= r_data[80:87];
	state[11] <= r_data[88:95];
	state[12] <= r_data[96:103];
	state[13] <= r_data[104:111];
	state[14] <= r_data[112:119];
	state[15] <= r_data[120:127];
end

// For Gtkwave debug
wire [0:7] state_0;
wire [0:7] state_1;
wire [0:7] state_2;
wire [0:7] state_3;
wire [0:7] state_4;
wire [0:7] state_5;
wire [0:7] state_6;
wire [0:7] state_7;
wire [0:7] state_8;
wire [0:7] state_9;
wire [0:7] state_10;
wire [0:7] state_11;
wire [0:7] state_12;
wire [0:7] state_13;
wire [0:7] state_14;
wire [0:7] state_15;

assign state_0 = state[0];
assign state_1 = state[1];
assign state_2 = state[2];
assign state_3 = state[3];
assign state_4 = state[4];
assign state_5 = state[5];
assign state_6 = state[6];
assign state_7 = state[7];
assign state_8 = state[8];
assign state_9 = state[9];
assign state_10 = state[10];
assign state_11 = state[11];
assign state_12 = state[12];
assign state_13 = state[13];
assign state_14 = state[14];
assign state_15 = state[15];

endmodule

aes/aes_tb.v
`timescale 1ns / 1ps

`include "aes.v"

module aes_tb();

// Testbench uses a 10 MHz clock
parameter c_CLOCK_PERIOD_NS = 100;

reg r_clock = 0;
reg [0:127] r_plain = 0;
reg [0:127] r_key = 0;
wire [0:127] w_cipher = 0;

aes_top aes_top_inst (
	.i_clock(r_clock),
	.i_plain(r_plain),
	.i_key(r_key),
	.o_cipher(w_cipher)
);

always
	#(c_CLOCK_PERIOD_NS/2) r_clock <= !r_clock;

initial begin
	$dumpfile("aes_tb.vcd");
	$dumpvars;

	@(posedge r_clock);
	r_plain <= 128'h00112233445566778899aabbccddeeff;
	r_key <= 128'h000102030405060708090a0b0c0d0e0f;

	#10000;
	$finish;
end
endmodule

aes/aes_tb.vcd
$date
	Mon Dec  2 00:05:01 2019
$end
$version
	Icarus Verilog
$end
$timescale
	1ps
$end
$scope module aes_tb $end
$var wire 128 ! w_cipher [0:127] $end
$var reg 1 " r_clock $end
$var reg 128 # r_key [0:127] $end
$var reg 128 $ r_plain [0:127] $end
$scope module aes_top_inst $end
$var wire 1 " i_clock $end
$var wire 128 % i_key [0:127] $end
$var wire 128 & i_plain [0:127] $end
$var wire 128 ' o_cipher [0:127] $end
$var wire 8 ( state_0 [0:7] $end
$var wire 8 ) state_1 [0:7] $end
$var wire 8 * state_10 [0:7] $end
$var wire 8 + state_11 [0:7] $end
$var wire 8 , state_12 [0:7] $end
$var wire 8 - state_13 [0:7] $end
$var wire 8 . state_14 [0:7] $end
$var wire 8 / state_15 [0:7] $end
$var wire 8 0 state_2 [0:7] $end
$var wire 8 1 state_3 [0:7] $end
$var wire 8 2 state_4 [0:7] $end
$var wire 8 3 state_5 [0:7] $end
$var wire 8 4 state_6 [0:7] $end
$var wire 8 5 state_7 [0:7] $end
$var wire 8 6 state_8 [0:7] $end
$var wire 8 7 state_9 [0:7] $end
$var wire 128 8 w_data_o_sub_byte [0:127] $end
$var wire 128 9 w_data_o_shift_rows [0:127] $end
$var reg 3 : clock_counter [0:2] $end
$var reg 128 ; r_data [0:127] $end
$var reg 1 < r_shift_rows_active $end
$var reg 3 = r_sm_main [2:0] $end
$var reg 1 > r_sub_bytes_active $end
$scope module shift_rows $end
$var wire 1 < i_active $end
$var wire 1 " i_clock $end
$var wire 128 ? i_data [0:127] $end
$var wire 128 @ o_data [0:127] $end
$var reg 128 A r_data [0:127] $end
$upscope $end
$scope module sub_bytes $end
$var wire 1 > i_active $end
$var wire 1 " i_clock $end
$var wire 128 B i_data [0:127] $end
$var wire 128 C o_data [0:127] $end
$var reg 128 D r_data [0:127] $end
$upscope $end
$upscope $end
$upscope $end
$enddefinitions $end
#0
$dumpvars
bx D
bx C
b0 B
bx A
bx @
b0 ?
0>
b0 =
0<
b0 ;
b0 :
bx 9
bx 8
b0 7
b0 6
b0 5
b0 4
b0 3
b0 2
b0 1
b0 0
b0 /
b0 .
b0 -
b0 ,
b0 +
b0 *
b0 )
b0 (
b0 '
b0 &
b0 %
b0 $
b0 #
0"
b0 !
$end
#50000
b1 =
b10000001000000011000001000000010100000110000001110000100000001001000010100000101100001100000011010000111000001111 #
b10000001000000011000001000000010100000110000001110000100000001001000010100000101100001100000011010000111000001111 %
b100010010001000110011010001000101010101100110011101111000100010011001101010101011101111001100110111011110111011111111 $
b100010010001000110011010001000101010101100110011101111000100010011001101010101011101111001100110111011110111011111111 &
1"
#100000
0"
#150000
b11111111 /
b11101110 .
b11011101 -
b11001100 ,
b10111011 +
b10101010 *
b10011001 7
b10001000 6
b1110111 5
b1100110 4
b1010101 3
b1000100 2
b110011 1
b100010 0
b10001 )
b10 =
b100010010001000110011010001000101010101100110011101111000100010011001101010101011101111001100110111011110111011111111 ;
b100010010001000110011010001000101010101100110011101111000100010011001101010101011101111001100110111011110111011111111 ?
b100010010001000110011010001000101010101100110011101111000100010011001101010101011101111001100110111011110111011111111 B
1"
#200000
0"
#250000
1>
b1 :
1"
#300000
0"
#350000
b1100011100000101001001111000011000110111111110000110011111101011100010011101110101011001110101001001011110000010010100000010110 8
b1100011100000101001001111000011000110111111110000110011111101011100010011101110101011001110101001001011110000010010100000010110 C
b1100011100000101001001111000011000110111111110000110011111101011100010011101110101011001110101001001011110000010010100000010110 D
b10 :
1"
#400000
0"
#450000
b10110 /
b101000 .
b11000001 -
b1001011 ,
b11101010 +
b10101100 *
b11101110 7
b11000100 6
b11110101 5
b110011 4
b11111100 3
b11011 2
b11000011 1
b10010011 0
b10000010 )
b1100011 (
b11 =
0>
b1100011100000101001001111000011000110111111110000110011111101011100010011101110101011001110101001001011110000010010100000010110 ;
b1100011100000101001001111000011000110111111110000110011111101011100010011101110101011001110101001001011110000010010100000010110 ?
b1100011100000101001001111000011000110111111110000110011111101011100010011101110101011001110101001001011110000010010100000010110 B
b0 :
1"
#500000
0"
#550000
1<
b1 :
1"
#600000
0"
#650000
b1100011100000101001001111000011111111000011001111110101000110111010110011101010110001001110111000010110010010111100000100101000 9
b1100011100000101001001111000011111111000011001111110101000110111010110011101010110001001110111000010110010010111100000100101000 @
b1100011100000101001001111000011111111000011001111110101000110111010110011101010110001001110111000010110010010111100000100101000 A
b10 :
1"
#700000
0"
#750000
b101000 /
b11000001 .
b1001011 -
b10110 ,
b11101110 +
b11000100 *
b11101010 7
b10101100 6
b11011 5
b11110101 4
b110011 3
b11111100 2
b100 =
0<
b1100011100000101001001111000011111111000011001111110101000110111010110011101010110001001110111000010110010010111100000100101000 ;
b1100011100000101001001111000011111111000011001111110101000110111010110011101010110001001110111000010110010010111100000100101000 ?
b1100011100000101001001111000011111111000011001111110101000110111010110011101010110001001110111000010110010010111100000100101000 B
b0 :
1"
